corvx/__init__.py
corvx/corvx.py
corvx/structures.py
corvx/version.py
corvx-1.2501.1.dist-info/LICENSE
corvx-1.2501.1.dist-info/METADATA
corvx-1.2501.1.dist-info/WHEEL
corvx-1.2501.1.dist-info/top_level.txt
corvx-1.2501.1.dist-info/RECORD
