Metadata-Version: 2.2
Name: corvx
Version: 1.2501.1
Summary: An unofficial X SDK for Python
Author-email: Rodrigo Martínez <dev@brunneis.com>
License: GNU General Public License v3 (GPLv3)
Project-URL: Repository, https://github.com/labteral/corvx
Classifier: Development Status :: 4 - Beta
Classifier: Environment :: Console
Classifier: Intended Audience :: Developers
Classifier: License :: OSI Approved :: GNU General Public License v3 (GPLv3)
Classifier: Operating System :: POSIX :: Linux
Classifier: Programming Language :: Python :: 3.10
Classifier: Programming Language :: Python :: Implementation :: PyPy
Classifier: Topic :: Software Development :: Libraries :: Python Modules
Requires-Python: >=3.10
License-File: LICENSE
Requires-Dist: requests
Requires-Dist: ordered-set
Provides-Extra: dev
Requires-Dist: build; extra == "dev"
Requires-Dist: installer; extra == "dev"
Requires-Dist: wheel; extra == "dev"
Requires-Dist: twine; extra == "dev"
